{
	"name": "WorldMapController",
	"plugin-id": "Sprite",
	"sid": 541630365289536,
	"isGlobal": false,
	"instanceVariables": [
		{
			"name": "overlayOpacity",
			"type": "number",
			"desc": "",
			"show": true,
			"sid": 956984792591142
		}
	],
	"behaviorTypes": [
		{
			"behaviorId": "Tween",
			"name": "Tween",
			"sid": 767643926753499
		}
	],
	"effectTypes": [],
	"animations": {
		"items": [
			{
				"frames": [
					{
						"width": 130,
						"height": 131,
						"originX": 0.46153846153846156,
						"originY": 0.44274809160305345,
						"originalSource": "",
						"exportFormat": "lossless",
						"exportQuality": 0.8,
						"imageSpriteId": 8741395,
						"useCollisionPoly": true,
						"duration": 1
					}
				],
				"sid": 301519241782890,
				"name": "Animation 1",
				"isLooping": false,
				"isPingPong": false,
				"repeatCount": 1,
				"repeatTo": 0,
				"speed": 5
			}
		],
		"subfolders": []
	}
}